README.rst
setup.py
cayenne/__init__.py
cayenne/client.py
cayenne_mqtt.egg-info/PKG-INFO
cayenne_mqtt.egg-info/SOURCES.txt
cayenne_mqtt.egg-info/dependency_links.txt
cayenne_mqtt.egg-info/requires.txt
cayenne_mqtt.egg-info/top_level.txt