Metadata-Version: 1.1
Name: cayenne-mqtt
Version: 1.1.0
Summary: Cayenne MQTT Python Library
Home-page: https://github.com/myDevicesIoT/Cayenne-MQTT-Python
Author: myDevices
Author-email: support@mydevices.com
License: MIT
Keywords: myDevices Cayenne MQTT
Platform: UNKNOWN
Classifier: Development Status :: 5 - Production/Stable
Classifier: Operating System :: MacOS :: MacOS X
Classifier: Operating System :: Microsoft :: Windows
Classifier: Operating System :: POSIX
Classifier: Programming Language :: Python
Classifier: License :: OSI Approved :: MIT License
Classifier: Intended Audience :: Developers
Classifier: Programming Language :: Python :: 2.7
Classifier: Programming Language :: Python :: 3.4
Classifier: Topic :: Software Development
Classifier: Topic :: Communications
Classifier: Topic :: Internet
Classifier: Topic :: Home Automation
Classifier: Topic :: System :: Monitoring
